Topsis_Python/Topsis_Nishant_101703375_COE17.py
Topsis_Python/__init__.py
Topsis_Python/cli.py
Topsis_Dhanda-0.4.dist-info/LICENSE
Topsis_Dhanda-0.4.dist-info/METADATA
Topsis_Dhanda-0.4.dist-info/WHEEL
Topsis_Dhanda-0.4.dist-info/entry_points.txt
Topsis_Dhanda-0.4.dist-info/top_level.txt
Topsis_Dhanda-0.4.dist-info/RECORD
