Metadata-Version: 2.1
Name: Topsis-Dhanda
Version: 0.4
Summary: A small package that showcases Topsis approach
Home-page: https://github.com/NishantDhanda/Topsis-Python.git
Author: Nishant Dhanda
Author-email: dhandanishant012@gmail.com
License: UNKNOWN
Download-URL: https://github.com/NishantDhanda/Topsis-Python/archive/0.01.tar.gz
Platform: UNKNOWN
Classifier: Programming Language :: Python :: 3
Classifier: License :: OSI Approved :: MIT License
Classifier: Operating System :: OS Independent
Requires-Python: >=3.6
